{
	"response": [
		{
			"maintainer": "Carlos Arriaga (TheStrechh)",
			"oem": "Xiaomi",
			"device": "Mi 9T",
			"filename": "crDroidAndroid-13.0-20221225-davinci-v9.0.zip",
			"download": "https://github.com/TheStrechh/thestrechh_builds/releases/download/20221225-1538/crDroidAndroid-13.0-20221225-davinci-v9.0.zip",
			"timestamp": 1671953270,
			"md5": "ad38c399666caee6ecdf714bddeded6a",
			"sha256": "bbe8c09c2b6331c0c4bf046b73c5e20ae92358fc30c950c24b071e93ae243a9e",
			"size": 1205761020,
			"version": "9.0",
			"buildtype": "Beta",
			"forum": "",
			"gapps": "",
			"firmware": "",
			"modem": "",
			"bootloader": "",
			"recovery": "",
			"paypal": "https://paypal.me/Strechh",
			"telegram": "https://t.me/TheStrechhSupportDavinci",
			"dt": "https://github.com/TheStrechh/android_device_xiaomi_davinci",
			"common-dt": "",
			"kernel": "https://github.com/TheStrechh/android_kernel_xiaomi_davinci"
		}
	]
}
